akr_agent/__init__.py
akr_agent/_version.py
akr_agent/agent.py
akr_agent/agent_config_engine.py
akr_agent/context_manager.py
akr_agent/dispatcher.py
akr_agent/event_bus.py
akr_agent/observable_ctx.py
akr_agent/output_stream_manager.py
akr_agent/rule_config.py
akr_agent/rule_registery.py
akr_agent/task_executor.py
akr_agent/task_manager.py
akr_agent/task_state.py
akr_agent/utils.py
akr_agent/workspace_manager.py
akr_agent/libs/__init__.py
akr_agent/libs/code/code_exec.py
akr_agent/libs/code/langfun_correction.py
akr_agent/libs/code/langfun_execution.py
akr_agent/libs/code/langfun_python_code.py
akr_agent/libs/code/parsing.py
akr_agent/libs/code/parsing_test.py
akr_agent/libs/crawler/crawl4ai.py
akr_agent/libs/search/__init__.py
akr_agent/libs/search/duckduckgo.py
akr_agent/libs/search/tavily.py
akr_agent/llm/__init__.py
akr_agent/llm/base.py
akr_agent/llm/llm_base.py
akr_agent/llm/llm_logger.py
akr_agent/llm/openai_client.py
akr_agent/tools/__init__.py
akr_agent/tools/base.py
akr_agent/tools/tool_code_repl.py
akr_agent/tools/tool_crawler.py
akr_agent/tools/tool_doc_index.py
akr_agent/tools/tool_llm.py
akr_agent/tools/tool_rag.py
akr_agent/tools/tool_search.py
akr_agent/tools/utils.py
akr_agent-0.1.3.dist-info/licenses/LICENSE
akr_agent-0.1.3.dist-info/METADATA
akr_agent-0.1.3.dist-info/WHEEL
akr_agent-0.1.3.dist-info/top_level.txt
akr_agent-0.1.3.dist-info/RECORD
