Metadata-Version: 2.4
Name: akr-agent
Version: 0.1.3
Summary: Akr Agent - A flexible rule-based AI Agent framework
Author-email: hongv <x.hiro.v@gmail.com>
License: MIT
Project-URL: Homepage, https://github.com/xhwSkhizein/akr-agent
Project-URL: Bug Tracker, https://github.com/xhwSkhizein/akr-agent/issues
Classifier: Development Status :: 3 - Alpha
Classifier: Intended Audience :: Developers
Classifier: License :: OSI Approved :: MIT License
Classifier: Programming Language :: Python :: 3
Classifier: Programming Language :: Python :: 3.8
Classifier: Programming Language :: Python :: 3.9
Classifier: Programming Language :: Python :: 3.10
Classifier: Programming Language :: Python :: 3.11
Requires-Python: >=3.8
License-File: LICENSE
Requires-Dist: jinja2
Requires-Dist: docstring-parser
Requires-Dist: pyyaml
Requires-Dist: duckduckgo-search
Requires-Dist: tavily-python
Provides-Extra: dev
Requires-Dist: pytest; extra == "dev"
Requires-Dist: pytest-asyncio; extra == "dev"
Requires-Dist: black; extra == "dev"
Requires-Dist: isort; extra == "dev"
Requires-Dist: mypy; extra == "dev"
Dynamic: license-file
